ccj_to_puz
