Metadata-Version: 1.0
Name: ccj-to-puz
Version: 0.2
Summary: Parse crosswords in .ccj format, and output in .puz format
Home-page: http://longair.net/blog/2009/07/24/avoiding-crossword-applets/
Author: Mark Longair
Author-email: mark-python@longair.net
License: GPL
Keywords: crossword crosswords
Platform: UNKNOWN
